snpy/__init__.py
snpy/bolometric.py
snpy/color_coefs.pickle
snpy/color_priors.pickle
snpy/dm15_calibration2.dat
snpy/get_osc.py
snpy/get_swift.py
snpy/interp_model.py
snpy/kcorr.py
snpy/lc.py
snpy/mangle_spectrum.py
snpy/mlcs_utils.py
snpy/model.py
snpy/myplotlib.py
snpy/plot_sne_mpl.py
snpy/plotmod.py
snpy/salt_utils.py
snpy/sn.py
snpy/snemcee.py
snpy/specobj.py
snpy/st_calibration2.dat
snpy/ubertemp.py
snpy/version.py
snpy/CSPtemp/__init__.py
snpy/CSPtemp/bs_error.pickle
snpy/CSPtemp/bs_error.py
snpy/CSPtemp/bs_surface.py
snpy/CSPtemp/dm15temp.h
snpy/CSPtemp/dm15temp2.py
snpy/CSPtemp/generate_surf.py
snpy/CSPtemp/gloes.h
snpy/CSPtemp/plot_bs_disps.py
snpy/CSPtemp/setup_old.py
snpy/CSPtemp/tck.pickle
snpy/CSPtemp/tck_destiny.pickle
snpy/CSPtemp/templates.dat
snpy/CSPtemp/fits/dm15_B_mean1.fits
snpy/CSPtemp/fits/dm15_B_mean2.fits
snpy/CSPtemp/fits/dm15_B_std1.fits
snpy/CSPtemp/fits/dm15_B_std2.fits
snpy/CSPtemp/fits/dm15_H_mean1.fits
snpy/CSPtemp/fits/dm15_H_mean2.fits
snpy/CSPtemp/fits/dm15_H_std1.fits
snpy/CSPtemp/fits/dm15_H_std2.fits
snpy/CSPtemp/fits/dm15_J_mean1.fits
snpy/CSPtemp/fits/dm15_J_mean2.fits
snpy/CSPtemp/fits/dm15_J_std1.fits
snpy/CSPtemp/fits/dm15_J_std2.fits
snpy/CSPtemp/fits/dm15_V_mean1.fits
snpy/CSPtemp/fits/dm15_V_mean2.fits
snpy/CSPtemp/fits/dm15_V_std1.fits
snpy/CSPtemp/fits/dm15_V_std2.fits
snpy/CSPtemp/fits/dm15_Y_mean1.fits
snpy/CSPtemp/fits/dm15_Y_mean2.fits
snpy/CSPtemp/fits/dm15_Y_std1.fits
snpy/CSPtemp/fits/dm15_Y_std2.fits
snpy/CSPtemp/fits/dm15_g_mean1.fits
snpy/CSPtemp/fits/dm15_g_mean2.fits
snpy/CSPtemp/fits/dm15_g_std1.fits
snpy/CSPtemp/fits/dm15_g_std2.fits
snpy/CSPtemp/fits/dm15_i_mean1.fits
snpy/CSPtemp/fits/dm15_i_mean2.fits
snpy/CSPtemp/fits/dm15_i_std1.fits
snpy/CSPtemp/fits/dm15_i_std2.fits
snpy/CSPtemp/fits/dm15_r_mean1.fits
snpy/CSPtemp/fits/dm15_r_mean2.fits
snpy/CSPtemp/fits/dm15_r_std1.fits
snpy/CSPtemp/fits/dm15_r_std2.fits
snpy/CSPtemp/fits/dm15_u_mean1.fits
snpy/CSPtemp/fits/dm15_u_mean2.fits
snpy-2.7.0.dist-info/LICENSE
snpy-2.7.0.dist-info/METADATA
snpy-2.7.0.dist-info/WHEEL
snpy-2.7.0.dist-info/top_level.txt
snpy-2.7.0.dist-info/RECORD
