Metadata-Version: 2.1
Name: snpy
Version: 2.7.0
Summary: SNooPy:  Supernova light-curve analysis tool
Author-email: Chris Burns <cburns@carnegiescience.edu>
License: SNooPy is distributed with the MIT license, reproduced below. If you use this
Keywords: astronomy,supernova,science
Classifier: Development Status :: 5 - Production/Stable
Classifier: Environment :: Console
Classifier: Framework :: IPython
Classifier: Intended Audience :: Science/Research
Classifier: License :: OSI Approved :: MIT License
Classifier: Programming Language :: Python :: 2
Classifier: Programming Language :: Python :: 2.6
Classifier: Programming Language :: Python :: 2.7
Classifier: Topic :: Scientific/Engineering :: Astronomy
Requires-Python: >=3.8
License-File: LICENSE
Requires-Dist: oldest-supported-numpy
Requires-Dist: scipy
Requires-Dist: astropy
Requires-Dist: ipython
Requires-Dist: matplotlib
Requires-Dist: pandas
Requires-Dist: pymysql
Requires-Dist: scikit-learn
Requires-Dist: h5py
Requires-Dist: onnxruntime
Requires-Dist: emcee
